dist
leaven
