Metadata-Version: 2.1
Name: leaven
Version: 1.1
Summary: A package bridging Python and Lean verification for proof search using language models
Home-page: https://github.com/xinhjBrant/leaven
Download-URL: https://github.com/user/reponame/archive/v_01.tar.gz
Author: Huajian Xin
Author-email: xinhuajian2000@gmail.com
License: MIT
Platform: all
Classifier: Intended Audience :: Developers
Classifier: Operating System :: OS Independent
Classifier: License :: OSI Approved :: MIT License
Classifier: Programming Language :: Python :: 3.9
Classifier: Topic :: Software Development :: Libraries
Requires-Python: >=3.9
License-File: LICENSE
Requires-Dist: networkx
Requires-Dist: pathlib
Requires-Dist: datetime
Requires-Dist: pytz
Requires-Dist: tqdm
